invisifox/__init__.py
invisifox/invisifoxApi.py
invisifox-0.0.5.dist-info/METADATA
invisifox-0.0.5.dist-info/WHEEL
invisifox-0.0.5.dist-info/top_level.txt
invisifox-0.0.5.dist-info/RECORD
