Metadata-Version: 2.1
Name: invisifox
Version: 0.0.5
Summary: Python module for easy integration with invisifox API
Home-page: UNKNOWN
Author: 100 Fire Limites
Author-email: <support@100fire.com>
License: UNKNOWN
Keywords: python,captcha,proxy,solver
Platform: UNKNOWN
Classifier: Development Status :: 1 - Planning
Classifier: Intended Audience :: Developers
Classifier: Programming Language :: Python :: 3
Classifier: Operating System :: Unix
Classifier: Operating System :: MacOS :: MacOS X
Classifier: Operating System :: Microsoft :: Windows
Requires-Dist: requests
